[
  {
    "id": "booking-1",
    "confirmationNumber": "A1B2C3D4",
    "serviceId": "service-1",
    "staffId": "staff-1",
    "date": "2025-10-25",
    "time": "10:00",
    "customerName": "Jamie Smith",
    "customerEmail": "jamie.smith@example.com",
    "customerPhone": "+27 82 123 4567",
    "totalPrice": 260.00,
    "status": "confirmed",
    "paymentStatus": "paid",
    "rating": 5,
    "review": "Excellent service! Very professional."
  },
  {
    "id": "booking-2",
    "confirmationNumber": "E5F6G7H8",
    "serviceId": "service-2",
    "staffId": "staff-3",
    "date": "2025-10-26",
    "time": "13:30",
    "customerName": "Casey Jones",
    "customerEmail": "casey.jones@example.com",
    "customerPhone": "+27 71 987 6543",
    "totalPrice": 565.00,
    "status": "confirmed",
    "paymentStatus": "paid",
    "rating": 4,
    "review": "Great styling, will come back!"
  },
  {
    "id": "booking-3",
    "confirmationNumber": "I9J0K1L2",
    "serviceId": "service-3",
    "staffId": "staff-2",
    "date": "2025-10-22",
    "time": "09:00",
    "customerName": "Riley Wilson",
    "customerEmail": "riley.wilson@example.com",
    "customerPhone": "+27 83 456 7890",
    "totalPrice": 125.00,
    "status": "cancelled",
    "paymentStatus": "refunded",
    "rating": null,
    "review": null,
    "refundAmount": 125.00,
    "cancellationReason": "Customer requested"
  },
  {
    "id": "booking-4",
    "confirmationNumber": "M3N4O5P6",
    "serviceId": "service-1",
    "staffId": "any",
    "date": "2025-10-28",
    "time": "11:00",
    "customerName": "Alex Thompson",
    "customerEmail": "alex.thompson@example.com",
    "customerPhone": "+27 84 234 5678",
    "totalPrice": 250.00,
    "status": "confirmed",
    "paymentStatus": "paid",
    "rating": null,
    "review": null
  },
  {
    "id": "booking-5",
    "confirmationNumber": "Q7R8S9T0",
    "serviceId": "service-2",
    "staffId": "staff-1",
    "date": "2025-10-27",
    "time": "14:00",
    "customerName": "Morgan Lee",
    "customerEmail": "morgan.lee@example.com",
    "customerPhone": "+27 72 345 6789",
    "totalPrice": 560.00,
    "status": "confirmed",
    "paymentStatus": "paid",
    "rating": 5,
    "review": "Amazing experience! Highly recommend Alex."
  },
  {
    "id": "booking-6",
    "confirmationNumber": "U1V2W3X4",
    "serviceId": "service-3",
    "staffId": "staff-2",
    "date": "2025-10-21",
    "time": "10:30",
    "customerName": "Taylor Swift",
    "customerEmail": "taylor.s@example.com",
    "customerPhone": "+27 81 456 7890",
    "totalPrice": 125.00,
    "status": "cancelled",
    "paymentStatus": "refunded",
    "rating": null,
    "review": null,
    "refundAmount": 125.00,
    "cancellationReason": "Schedule conflict"
  }
]
